setup.cfg
setup.py
kryptonium/__init__.py
kryptonium/components.py
kryptonium/connection.py
kryptonium/driver.py
kryptonium/elements.py
kryptonium/pages.py
kryptonium/utils.py
kryptonium.egg-info/PKG-INFO
kryptonium.egg-info/SOURCES.txt
kryptonium.egg-info/dependency_links.txt
kryptonium.egg-info/not-zip-safe
kryptonium.egg-info/requires.txt
kryptonium.egg-info/top_level.txt