Metadata-Version: 1.0
Name: kryptonium
Version: 0.1.4
Summary: Automation Framework using Selenium
Home-page: https://github.com/danggrianto/kryptonium
Author: Daniel Anggrianto
Author-email: daniel@anggrianto.com
License: GNU GPL v2.0
Platform: any
